{"Id":"132","ThresholdLowerCritical":null,"EntityInstance":1,"Assertion":"Deassert","@odata.etag":"W/\"b546470ad2780ebeba25fd7d28abc2c9\"","@odata.context":"/redfish/v1/$metadata#LenovoSensor.LenovoSensor","@odata.id":"/redfish/v1/Chassis/1/Oem/Lenovo/Sensors/132","Description":"This resource is used to represent a sensor for a Redfish implementation.","ThresholdLowerNonCritical":null,"SensorNumber":132,"OwnerLUN":0,"RecordType":1,"UnitModifier":0,"ThresholdUpperNonCritical":null,"OwnerID":16,"State":192,"SensorType":"Temperature","ReadingType":1,"ThresholdUpperFatal":null,"ThresholdLowerFatal":null,"Name":"CPU1 Temp","@odata.type":"#LenovoSensor.v1_0_0.LenovoSensor","EntityID":3,"ThresholdUpperCritical":null,"BaseUnit":"1","SensorTypeNumber":1,"Reading":31}