{
    "@odata.context": "/redfish/v1/$metadata#LenovoSensor.LenovoSensor",
    "@odata.etag": "W/\"69e23e93257dbd17fc139cffa192f3eb\"",
    "@odata.id": "/redfish/v1/Chassis/1/Oem/Lenovo/Sensors/227",
    "@odata.type": "#LenovoSensor.v1_0_0.LenovoSensor",
    "Assertion": "Assert",
    "BaseUnit": "0",
    "Description": "This resource is used to represent a sensor for a Redfish implementation.",
    "EntityID": 15,
    "EntityInstance": 1,
    "Id": "227",
    "Name": "BP 1 Status",
    "OwnerID": 16,
    "OwnerLUN": 0,
    "Reading": 0,
    "ReadingType": 111,
    "RecordType": 2,
    "SensorNumber": 227,
    "SensorType": "Entity Presence",
    "SensorTypeNumber": 37,
    "State": 32769
}
