{"Id":"BMC","Description":"This resource is used to represent a firmware service for a Redfish implementation.","Firmwares":[{"@odata.id":"/redfish/v1/UpdateService/FirmwareInventory/BMC-Primary"},{"@odata.id":"/redfish/v1/UpdateService/FirmwareInventory/BMC-Backup"}],"Name":"LenovoFirmwareService","@odata.context":"/redfish/v1/$metadata#LenovoFirmwareService.LenovoFirmwareService","@odata.id":"/redfish/v1/Oem/Lenovo/FirmwareServices/BMC","Actions":{"#LenovoFirmwareService.InstallFromURI":{"target":"/redfish/v1/Oem/Lenovo/FirmwareServices/BMC/Actions/LenovoFirmwareService.InstallFromURI","InstallOptions@Redfish.AllowableValues":["Install"],"title":"InstallFromURI"}},"@odata.type":"#LenovoFirmwareService.v1_0_0.LenovoFirmwareService","Task":{"@odata.id":"/redfish/v1/Tasks/Tasks/"},"AutoPromotion":true,"@odata.etag":"W/\"1e22496494b7e01b2a9584c762b16530\"","ChangeHistory":{"@odata.id":"/redfish/v1/Systems/1/LogServices/"},"@Redfish.Deprecated":"The BMC FirmwareService is deprecated. Please use UpdateService instead."}