{
    "@odata.context": "/redfish/v1/$metadata#JsonSchemaFile.JsonSchemaFile",
    "@odata.etag": "W/\"4b18261d36ad447b1b42089f9874f433\"",
    "@odata.id": "/redfish/v1/JsonSchemas/LenovoRemoteControlSession",
    "@odata.type": "#JsonSchemaFile.v1_1_0.JsonSchemaFile",
    "Description": "LenovoRemoteControlSession schema information",
    "Id": "LenovoRemoteControlSession",
    "Languages": [
        "en"
    ],
    "Location": [
        {
            "Language": "en",
            "Uri": "/redfish/v1/schemas/LenovoRemoteControlSession.json"
        }
    ],
    "Name": "LenovoRemoteControlSession JSON Schema File",
    "Schema": "#LenovoRemoteControlSession.LenovoRemoteControlSession"
}
