{
    "@odata.context": "/redfish/v1/$metadata#LenovoManagerGroup.LenovoManagerGroup",
    "@odata.etag": "W/\"68103c7e7fc882d872ed9a35a79add51\"",
    "@odata.id": "/redfish/v1/AccountService/Oem/Lenovo/GroupProfiles/Group11",
    "@odata.type": "#LenovoManagerGroup.v1_0_0.LenovoManagerGroup",
    "Description": "This resource is used to represent a group profile on the manager for a Redfish implementation.",
    "GroupName": "",
    "Id": "Group11",
    "Links": {
        "Role": {
            "@odata.id": "/redfish/v1/AccountService/Roles/"
        }
    },
    "Name": "LenovoManagerGroup",
    "Privilege": []
}
