{
    "@odata.context": "/redfish/v1/$metadata#JsonSchemaFile.JsonSchemaFile",
    "@odata.etag": "W/\"4306c715ec1aadc4e04f228667ab154f\"",
    "@odata.id": "/redfish/v1/JsonSchemas/LenovoSecurityService",
    "@odata.type": "#JsonSchemaFile.v1_1_0.JsonSchemaFile",
    "Description": "LenovoSecurityService schema information",
    "Id": "LenovoSecurityService",
    "Languages": [
        "en"
    ],
    "Location": [
        {
            "Language": "en",
            "Uri": "/redfish/v1/schemas/LenovoSecurityService.json"
        }
    ],
    "Name": "LenovoSecurityService JSON Schema File",
    "Schema": "#LenovoSecurityService.LenovoSecurityService"
}
